__init__.py
parsehub/__init__.py
parsehub/main.py
parsehub/config/__init__.py
parsehub/config/config.py
parsehub/parsers/__init__.py
parsehub/parsers/base/__init__.py
parsehub/parsers/base/base.py
parsehub/parsers/base/yt_dlp_parser.py
parsehub/parsers/parser/__init__.py
parsehub/parsers/parser/bilibili.py
parsehub/parsers/parser/coolapk.py
parsehub/parsers/parser/douyin.py
parsehub/parsers/parser/facebook.py
parsehub/parsers/parser/instagram.py
parsehub/parsers/parser/kuaishou.py
parsehub/parsers/parser/pipix.py
parsehub/parsers/parser/threads.py
parsehub/parsers/parser/tieba.py
parsehub/parsers/parser/twitter.py
parsehub/parsers/parser/weibo.py
parsehub/parsers/parser/weixin.py
parsehub/parsers/parser/xhs.py
parsehub/parsers/parser/youtube.py
parsehub/parsers/parser/zuiyou.py
parsehub/provider_api/__init__.py
parsehub/provider_api/bilibili.py
parsehub/provider_api/coolapk.py
parsehub/provider_api/instagram.py
parsehub/provider_api/kuaishou.py
parsehub/provider_api/pipix.py
parsehub/provider_api/threads.py
parsehub/provider_api/tieba.py
parsehub/provider_api/twitter.py
parsehub/provider_api/weibo.py
parsehub/provider_api/weixin.py
parsehub/provider_api/xhs.py
parsehub/provider_api/zuiyou.py
parsehub/tools/__init__.py
parsehub/tools/llm.py
parsehub/tools/transcriptions.py
parsehub/types/__init__.py
parsehub/types/error.py
parsehub/types/media.py
parsehub/types/parse_result.py
parsehub/types/subtitles.py
parsehub/types/summary_result.py
parsehub/utiles/azure.py
parsehub/utiles/download_file.py
parsehub/utiles/img_host.py
parsehub/utiles/utile.py
parsehub/utiles/whisper_api.py
parsehub-1.5.12.dist-info/licenses/LICENSE
parsehub-1.5.12.dist-info/METADATA
parsehub-1.5.12.dist-info/WHEEL
parsehub-1.5.12.dist-info/top_level.txt
parsehub-1.5.12.dist-info/RECORD
