Metadata-Version: 2.4
Name: parsehub
Version: 1.5.12
Summary: 支持AI总结的社交媒体聚合解析器
Author-email: 梓澪 <zilingmio@gmail.com>
License: MIT
Project-URL: Repository, https://github.com/z-mio/parsehub
Project-URL: Issues, https://github.com/z-mio/parsehub/issues
Requires-Python: >=3.12.0
License-File: LICENSE
Requires-Dist: aiofiles<24.dev0,>=23.2
Requires-Dist: beautifulsoup4>=4.12.3
Requires-Dist: dynamicadaptor>=0.5.2
Requires-Dist: dynrender-skia>=0.2.5
Requires-Dist: langchain>=0.2.5
Requires-Dist: langchain-core>=0.2.8
Requires-Dist: langchain-openai>=0.1.14
Requires-Dist: loguru>=0.6.0
Requires-Dist: openai>=1.54.5
Requires-Dist: opencv-python>=4.10.0.84
Requires-Dist: pydub>=0.25.1
Requires-Dist: python-dotenv>=1.0.1
Requires-Dist: tenacity>=8.5.0
Requires-Dist: urlextract>=1.9.0
Requires-Dist: yt-dlp[default]
Requires-Dist: lxml>=5.3.0
Requires-Dist: instaloader>=4.14
Requires-Dist: pydantic>=1.10.19
Requires-Dist: markdownify>=1.1.0
Requires-Dist: markdown>=3.7
Requires-Dist: requests
Requires-Dist: skia-python>=87.6
Requires-Dist: httpx>=0.24.1
Requires-Dist: pydantic-settings>=2.10.1
Requires-Dist: ruff>=0.14.14
Requires-Dist: pillow>=12.1.0
Dynamic: license-file
